docker_recipe/__init__.py
docker_recipe/cli.py
docker_recipe/data_structure.py
docker_recipe/filters.py
docker_recipe/main.py
docker_recipe-2.0.0.dist-info/LICENSE.md
docker_recipe-2.0.0.dist-info/METADATA
docker_recipe-2.0.0.dist-info/WHEEL
docker_recipe-2.0.0.dist-info/entry_points.txt
docker_recipe-2.0.0.dist-info/top_level.txt
docker_recipe-2.0.0.dist-info/RECORD
