Metadata-Version: 2.1
Name: docker-recipe
Version: 2.0.0
Summary: A way to cook multiple Dockerfiles
Home-page: https://github.com/stephanmeijer/docker-recipe
Author: Stephan Meijer
Author-email: me@stephanmeijer.com
Classifier: License :: OSI Approved :: GNU General Public License v3 (GPLv3)
Classifier: Programming Language :: Python :: 3
Classifier: Programming Language :: Python :: 3.6
License-File: LICENSE.md
Requires-Dist: pydantic (~=1.10.8)
Requires-Dist: PyYaml (~=6.0)
Requires-Dist: Jinja2 (~=3.1.2)
